binopt/__init__.py
binopt/core.py
binopt/stats.py
binopt/tfbinner.py
binopt/tools.py
binopt-0.2.1.dist-info/DESCRIPTION.rst
binopt-0.2.1.dist-info/METADATA
binopt-0.2.1.dist-info/RECORD
binopt-0.2.1.dist-info/WHEEL
binopt-0.2.1.dist-info/entry_points.txt
binopt-0.2.1.dist-info/metadata.json
binopt-0.2.1.dist-info/top_level.txt
