Metadata-Version: 2.0
Name: binopt
Version: 0.2.1
Summary: Categorisation of labeled data
Home-page: https://github.com/yhaddad/binopt
Author: Yacine Haddad
Author-email: yhaddad@cern.ch
License: GNU General Public License v3
Keywords: binopt
Platform: UNKNOWN
Classifier: Development Status :: 2 - Pre-Alpha
Classifier: Intended Audience :: Developers
Classifier: License :: OSI Approved :: GNU General Public License v3 (GPLv3)
Classifier: Natural Language :: English
Classifier: Programming Language :: Python :: 2.7
Requires-Dist: Click (>=6.0)
Requires-Dist: scipy
Requires-Dist: numpy
Requires-Dist: matplotlib
Requires-Dist: pip (>=8.1.2)
Requires-Dist: bumpversion (>=0.5.3)
Requires-Dist: wheel (>=0.29.0)
Requires-Dist: watchdog (>=0.8.3)
Requires-Dist: flake8 (>=2.6.0)
Requires-Dist: coverage (>=4.1)
Requires-Dist: Sphinx (>=1.4.8)
Requires-Dist: PyYAML (>=3.11)
